ocsf/__init__.py
ocsf/events/__init__.py
ocsf/events/base.py
ocsf/events/application/__init__.py
ocsf/events/application/api.py
ocsf/events/application/application.py
ocsf/events/application/application_lifecycle.py
ocsf/events/application/datastore.py
ocsf/events/application/file_hosting.py
ocsf/events/application/scan.py
ocsf/events/application/web_resource_access.py
ocsf/events/application/web_resources.py
ocsf/events/discovery/__init__.py
ocsf/events/discovery/config_state.py
ocsf/events/discovery/device_config_state_change.py
ocsf/events/discovery/discovery.py
ocsf/events/discovery/file_query.py
ocsf/events/discovery/folder_query.py
ocsf/events/discovery/group_query.py
ocsf/events/discovery/inventory_info.py
ocsf/events/discovery/job_query.py
ocsf/events/discovery/kernel_object_query.py
ocsf/events/discovery/module_query.py
ocsf/events/discovery/network_connection_query.py
ocsf/events/discovery/networks_query.py
ocsf/events/discovery/patch_state.py
ocsf/events/discovery/peripheral_device_query.py
ocsf/events/discovery/process_query.py
ocsf/events/discovery/service_query.py
ocsf/events/discovery/session_query.py
ocsf/events/discovery/user_inventory.py
ocsf/events/discovery/user_query.py
ocsf/events/findings/__init__.py
ocsf/events/findings/compliance.py
ocsf/events/findings/data_security.py
ocsf/events/findings/detection.py
ocsf/events/findings/finding.py
ocsf/events/findings/incident.py
ocsf/events/findings/vulnerability.py
ocsf/events/iam/__init__.py
ocsf/events/iam/account_change.py
ocsf/events/iam/authentication.py
ocsf/events/iam/authorize_session.py
ocsf/events/iam/entity_management.py
ocsf/events/iam/group_management.py
ocsf/events/iam/iam.py
ocsf/events/iam/user_access.py
ocsf/events/network/__init__.py
ocsf/events/network/dhcp.py
ocsf/events/network/dns.py
ocsf/events/network/email.py
ocsf/events/network/email_file.py
ocsf/events/network/email_url.py
ocsf/events/network/file_activity.py
ocsf/events/network/ftp.py
ocsf/events/network/http.py
ocsf_pydantic-0.0.6.dist-info/LICENSE
ocsf_pydantic-0.0.6.dist-info/METADATA
ocsf_pydantic-0.0.6.dist-info/WHEEL
ocsf_pydantic-0.0.6.dist-info/top_level.txt
ocsf_pydantic-0.0.6.dist-info/RECORD
