Metadata-Version: 2.1
Name: ocsf-pydantic
Version: 0.0.6
Summary: Pydantic models for OCSF
Author-email: "Crowdalert, Inc" <hello@crowdalert.com>
License: MIT License
Project-URL: Homepage, https://github.com/crowdalert/ocsf-pydantic
Classifier: Programming Language :: Python :: 3
Classifier: License :: OSI Approved :: MIT License
Classifier: Operating System :: OS Independent
Requires-Python: >=3.9
License-File: LICENSE
